{
  "generated_at": "2026-04-23T19:19:58.909563+00:00",
  "payload": {
    "items": [
      {
        "stock_code": "600050",
        "trade_date": "2025-12-22",
        "open_price": 5.17,
        "close_price": 5.14,
        "high_price": 5.19,
        "low_price": 5.14,
        "volume": 114731128,
        "turnover": 0.0,
        "adj_type": "none",
        "source_type": "sina_history_kline",
        "source_url": "https://money.finance.sina.com.cn/quotes_service/api/json_v2.php/CN_MarketData.getKLineData?symbol=600050"
      },
      {
        "stock_code": "600050",
        "trade_date": "2025-12-23",
        "open_price": 5.13,
        "close_price": 5.11,
        "high_price": 5.14,
        "low_price": 5.1,
        "volume": 100184918,
        "turnover": 0.0,
        "adj_type": "none",
        "source_type": "sina_history_kline",
        "source_url": "https://money.finance.sina.com.cn/quotes_service/api/json_v2.php/CN_MarketData.getKLineData?symbol=600050"
      },
      {
        "stock_code": "600050",
        "trade_date": "2025-12-24",
        "open_price": 5.11,
        "close_price": 5.13,
        "high_price": 5.15,
        "low_price": 5.1,
        "volume": 89821587,
        "turnover": 0.0,
        "adj_type": "none",
        "source_type": "sina_history_kline",
        "source_url": "https://money.finance.sina.com.cn/quotes_service/api/json_v2.php/CN_MarketData.getKLineData?symbol=600050"
      },
      {
        "stock_code": "600050",
        "trade_date": "2025-12-25",
        "open_price": 5.13,
        "close_price": 5.14,
        "high_price": 5.15,
        "low_price": 5.12,
        "volume": 81419061,
        "turnover": 0.0,
        "adj_type": "none",
        "source_type": "sina_history_kline",
        "source_url": "https://money.finance.sina.com.cn/quotes_service/api/json_v2.php/CN_MarketData.getKLineData?symbol=600050"
      },
      {
        "stock_code": "600050",
        "trade_date": "2025-12-26",
        "open_price": 5.14,
        "close_price": 5.14,
        "high_price": 5.15,
        "low_price": 5.11,
        "volume": 118407026,
        "turnover": 0.0,
        "adj_type": "none",
        "source_type": "sina_history_kline",
        "source_url": "https://money.finance.sina.com.cn/quotes_service/api/json_v2.php/CN_MarketData.getKLineData?symbol=600050"
      },
      {
        "stock_code": "600050",
        "trade_date": "2025-12-29",
        "open_price": 5.13,
        "close_price": 5.11,
        "high_price": 5.14,
        "low_price": 5.1,
        "volume": 113635720,
        "turnover": 0.0,
        "adj_type": "none",
        "source_type": "sina_history_kline",
        "source_url": "https://money.finance.sina.com.cn/quotes_service/api/json_v2.php/CN_MarketData.getKLineData?symbol=600050"
      },
      {
        "stock_code": "600050",
        "trade_date": "2025-12-30",
        "open_price": 5.1,
        "close_price": 5.09,
        "high_price": 5.12,
        "low_price": 5.07,
        "volume": 140253655,
        "turnover": 0.0,
        "adj_type": "none",
        "source_type": "sina_history_kline",
        "source_url": "https://money.finance.sina.com.cn/quotes_service/api/json_v2.php/CN_MarketData.getKLineData?symbol=600050"
      },
      {
        "stock_code": "600050",
        "trade_date": "2025-12-31",
        "open_price": 5.08,
        "close_price": 5.11,
        "high_price": 5.12,
        "low_price": 5.08,
        "volume": 107767318,
        "turnover": 0.0,
        "adj_type": "none",
        "source_type": "sina_history_kline",
        "source_url": "https://money.finance.sina.com.cn/quotes_service/api/json_v2.php/CN_MarketData.getKLineData?symbol=600050"
      },
      {
        "stock_code": "600050",
        "trade_date": "2026-01-05",
        "open_price": 5.13,
        "close_price": 5.16,
        "high_price": 5.16,
        "low_price": 5.11,
        "volume": 191928834,
        "turnover": 0.0,
        "adj_type": "none",
        "source_type": "sina_history_kline",
        "source_url": "https://money.finance.sina.com.cn/quotes_service/api/json_v2.php/CN_MarketData.getKLineData?symbol=600050"
      },
      {
        "stock_code": "600050",
        "trade_date": "2026-01-06",
        "open_price": 5.15,
        "close_price": 5.22,
        "high_price": 5.23,
        "low_price": 5.14,
        "volume": 211698652,
        "turnover": 0.0,
        "adj_type": "none",
        "source_type": "sina_history_kline",
        "source_url": "https://money.finance.sina.com.cn/quotes_service/api/json_v2.php/CN_MarketData.getKLineData?symbol=600050"
      },
      {
        "stock_code": "600050",
        "trade_date": "2026-01-07",
        "open_price": 5.22,
        "close_price": 5.16,
        "high_price": 5.22,
        "low_price": 5.15,
        "volume": 178337340,
        "turnover": 0.0,
        "adj_type": "none",
        "source_type": "sina_history_kline",
        "source_url": "https://money.finance.sina.com.cn/quotes_service/api/json_v2.php/CN_MarketData.getKLineData?symbol=600050"
      },
      {
        "stock_code": "600050",
        "trade_date": "2026-01-08",
        "open_price": 5.15,
        "close_price": 5.25,
        "high_price": 5.33,
        "low_price": 5.13,
        "volume": 372748791,
        "turnover": 0.0,
        "adj_type": "none",
        "source_type": "sina_history_kline",
        "source_url": "https://money.finance.sina.com.cn/quotes_service/api/json_v2.php/CN_MarketData.getKLineData?symbol=600050"
      },
      {
        "stock_code": "600050",
        "trade_date": "2026-01-09",
        "open_price": 5.22,
        "close_price": 5.42,
        "high_price": 5.49,
        "low_price": 5.22,
        "volume": 652641848,
        "turnover": 0.0,
        "adj_type": "none",
        "source_type": "sina_history_kline",
        "source_url": "https://money.finance.sina.com.cn/quotes_service/api/json_v2.php/CN_MarketData.getKLineData?symbol=600050"
      },
      {
        "stock_code": "600050",
        "trade_date": "2026-01-12",
        "open_price": 5.42,
        "close_price": 5.49,
        "high_price": 5.53,
        "low_price": 5.42,
        "volume": 647253805,
        "turnover": 0.0,
        "adj_type": "none",
        "source_type": "sina_history_kline",
        "source_url": "https://money.finance.sina.com.cn/quotes_service/api/json_v2.php/CN_MarketData.getKLineData?symbol=600050"
      },
      {
        "stock_code": "600050",
        "trade_date": "2026-01-13",
        "open_price": 5.48,
        "close_price": 5.37,
        "high_price": 5.49,
        "low_price": 5.35,
        "volume": 470429945,
        "turnover": 0.0,
        "adj_type": "none",
        "source_type": "sina_history_kline",
        "source_url": "https://money.finance.sina.com.cn/quotes_service/api/json_v2.php/CN_MarketData.getKLineData?symbol=600050"
      },
      {
        "stock_code": "600050",
        "trade_date": "2026-01-14",
        "open_price": 5.35,
        "close_price": 5.34,
        "high_price": 5.45,
        "low_price": 5.31,
        "volume": 361016079,
        "turnover": 0.0,
        "adj_type": "none",
        "source_type": "sina_history_kline",
        "source_url": "https://money.finance.sina.com.cn/quotes_service/api/json_v2.php/CN_MarketData.getKLineData?symbol=600050"
      },
      {
        "stock_code": "600050",
        "trade_date": "2026-01-15",
        "open_price": 5.31,
        "close_price": 5.24,
        "high_price": 5.33,
        "low_price": 5.22,
        "volume": 308739876,
        "turnover": 0.0,
        "adj_type": "none",
        "source_type": "sina_history_kline",
        "source_url": "https://money.finance.sina.com.cn/quotes_service/api/json_v2.php/CN_MarketData.getKLineData?symbol=600050"
      },
      {
        "stock_code": "600050",
        "trade_date": "2026-01-16",
        "open_price": 5.25,
        "close_price": 5.15,
        "high_price": 5.27,
        "low_price": 5.13,
        "volume": 310335546,
        "turnover": 0.0,
        "adj_type": "none",
        "source_type": "sina_history_kline",
        "source_url": "https://money.finance.sina.com.cn/quotes_service/api/json_v2.php/CN_MarketData.getKLineData?symbol=600050"
      },
      {
        "stock_code": "600050",
        "trade_date": "2026-01-19",
        "open_price": 5.13,
        "close_price": 5.15,
        "high_price": 5.18,
        "low_price": 5.11,
        "volume": 226863652,
        "turnover": 0.0,
        "adj_type": "none",
        "source_type": "sina_history_kline",
        "source_url": "https://money.finance.sina.com.cn/quotes_service/api/json_v2.php/CN_MarketData.getKLineData?symbol=600050"
      },
      {
        "stock_code": "600050",
        "trade_date": "2026-01-20",
        "open_price": 5.15,
        "close_price": 5.14,
        "high_price": 5.15,
        "low_price": 5.11,
        "volume": 232900137,
        "turnover": 0.0,
        "adj_type": "none",
        "source_type": "sina_history_kline",
        "source_url": "https://money.finance.sina.com.cn/quotes_service/api/json_v2.php/CN_MarketData.getKLineData?symbol=600050"
      },
      {
        "stock_code": "600050",
        "trade_date": "2026-01-21",
        "open_price": 5.13,
        "close_price": 5.08,
        "high_price": 5.14,
        "low_price": 5.07,
        "volume": 332315068,
        "turnover": 0.0,
        "adj_type": "none",
        "source_type": "sina_history_kline",
        "source_url": "https://money.finance.sina.com.cn/quotes_service/api/json_v2.php/CN_MarketData.getKLineData?symbol=600050"
      },
      {
        "stock_code": "600050",
        "trade_date": "2026-01-22",
        "open_price": 5.09,
        "close_price": 5.09,
        "high_price": 5.13,
        "low_price": 5.08,
        "volume": 252436649,
        "turnover": 0.0,
        "adj_type": "none",
        "source_type": "sina_history_kline",
        "source_url": "https://money.finance.sina.com.cn/quotes_service/api/json_v2.php/CN_MarketData.getKLineData?symbol=600050"
      },
      {
        "stock_code": "600050",
        "trade_date": "2026-01-23",
        "open_price": 5.1,
        "close_price": 5.12,
        "high_price": 5.13,
        "low_price": 5.09,
        "volume": 274643660,
        "turnover": 0.0,
        "adj_type": "none",
        "source_type": "sina_history_kline",
        "source_url": "https://money.finance.sina.com.cn/quotes_service/api/json_v2.php/CN_MarketData.getKLineData?symbol=600050"
      },
      {
        "stock_code": "600050",
        "trade_date": "2026-01-26",
        "open_price": 5.12,
        "close_price": 5.1,
        "high_price": 5.16,
        "low_price": 5.09,
        "volume": 297444744,
        "turnover": 0.0,
        "adj_type": "none",
        "source_type": "sina_history_kline",
        "source_url": "https://money.finance.sina.com.cn/quotes_service/api/json_v2.php/CN_MarketData.getKLineData?symbol=600050"
      },
      {
        "stock_code": "600050",
        "trade_date": "2026-01-27",
        "open_price": 5.1,
        "close_price": 5.07,
        "high_price": 5.11,
        "low_price": 5.06,
        "volume": 245851451,
        "turnover": 0.0,
        "adj_type": "none",
        "source_type": "sina_history_kline",
        "source_url": "https://money.finance.sina.com.cn/quotes_service/api/json_v2.php/CN_MarketData.getKLineData?symbol=600050"
      },
      {
        "stock_code": "600050",
        "trade_date": "2026-01-28",
        "open_price": 5.08,
        "close_price": 5.15,
        "high_price": 5.21,
        "low_price": 5.08,
        "volume": 561519220,
        "turnover": 0.0,
        "adj_type": "none",
        "source_type": "sina_history_kline",
        "source_url": "https://money.finance.sina.com.cn/quotes_service/api/json_v2.php/CN_MarketData.getKLineData?symbol=600050"
      },
      {
        "stock_code": "600050",
        "trade_date": "2026-01-29",
        "open_price": 5.13,
        "close_price": 5.15,
        "high_price": 5.17,
        "low_price": 5.1,
        "volume": 360980688,
        "turnover": 0.0,
        "adj_type": "none",
        "source_type": "sina_history_kline",
        "source_url": "https://money.finance.sina.com.cn/quotes_service/api/json_v2.php/CN_MarketData.getKLineData?symbol=600050"
      },
      {
        "stock_code": "600050",
        "trade_date": "2026-01-30",
        "open_price": 5.12,
        "close_price": 5.11,
        "high_price": 5.17,
        "low_price": 5.07,
        "volume": 266514038,
        "turnover": 0.0,
        "adj_type": "none",
        "source_type": "sina_history_kline",
        "source_url": "https://money.finance.sina.com.cn/quotes_service/api/json_v2.php/CN_MarketData.getKLineData?symbol=600050"
      },
      {
        "stock_code": "600050",
        "trade_date": "2026-02-02",
        "open_price": 4.99,
        "close_price": 4.83,
        "high_price": 5.0,
        "low_price": 4.83,
        "volume": 557781622,
        "turnover": 0.0,
        "adj_type": "none",
        "source_type": "sina_history_kline",
        "source_url": "https://money.finance.sina.com.cn/quotes_service/api/json_v2.php/CN_MarketData.getKLineData?symbol=600050"
      },
      {
        "stock_code": "600050",
        "trade_date": "2026-02-03",
        "open_price": 4.86,
        "close_price": 4.81,
        "high_price": 4.87,
        "low_price": 4.78,
        "volume": 255973854,
        "turnover": 0.0,
        "adj_type": "none",
        "source_type": "sina_history_kline",
        "source_url": "https://money.finance.sina.com.cn/quotes_service/api/json_v2.php/CN_MarketData.getKLineData?symbol=600050"
      },
      {
        "stock_code": "600050",
        "trade_date": "2026-02-04",
        "open_price": 4.8,
        "close_price": 4.87,
        "high_price": 4.87,
        "low_price": 4.78,
        "volume": 207291783,
        "turnover": 0.0,
        "adj_type": "none",
        "source_type": "sina_history_kline",
        "source_url": "https://money.finance.sina.com.cn/quotes_service/api/json_v2.php/CN_MarketData.getKLineData?symbol=600050"
      },
      {
        "stock_code": "600050",
        "trade_date": "2026-02-05",
        "open_price": 4.85,
        "close_price": 4.88,
        "high_price": 4.89,
        "low_price": 4.84,
        "volume": 186991760,
        "turnover": 0.0,
        "adj_type": "none",
        "source_type": "sina_history_kline",
        "source_url": "https://money.finance.sina.com.cn/quotes_service/api/json_v2.php/CN_MarketData.getKLineData?symbol=600050"
      },
      {
        "stock_code": "600050",
        "trade_date": "2026-02-06",
        "open_price": 4.86,
        "close_price": 4.84,
        "high_price": 4.87,
        "low_price": 4.83,
        "volume": 146099461,
        "turnover": 0.0,
        "adj_type": "none",
        "source_type": "sina_history_kline",
        "source_url": "https://money.finance.sina.com.cn/quotes_service/api/json_v2.php/CN_MarketData.getKLineData?symbol=600050"
      },
      {
        "stock_code": "600050",
        "trade_date": "2026-02-09",
        "open_price": 4.86,
        "close_price": 4.86,
        "high_price": 4.87,
        "low_price": 4.84,
        "volume": 135095774,
        "turnover": 0.0,
        "adj_type": "none",
        "source_type": "sina_history_kline",
        "source_url": "https://money.finance.sina.com.cn/quotes_service/api/json_v2.php/CN_MarketData.getKLineData?symbol=600050"
      },
      {
        "stock_code": "600050",
        "trade_date": "2026-02-10",
        "open_price": 4.86,
        "close_price": 4.87,
        "high_price": 4.88,
        "low_price": 4.84,
        "volume": 145114727,
        "turnover": 0.0,
        "adj_type": "none",
        "source_type": "sina_history_kline",
        "source_url": "https://money.finance.sina.com.cn/quotes_service/api/json_v2.php/CN_MarketData.getKLineData?symbol=600050"
      },
      {
        "stock_code": "600050",
        "trade_date": "2026-02-11",
        "open_price": 4.87,
        "close_price": 4.86,
        "high_price": 4.89,
        "low_price": 4.85,
        "volume": 109463571,
        "turnover": 0.0,
        "adj_type": "none",
        "source_type": "sina_history_kline",
        "source_url": "https://money.finance.sina.com.cn/quotes_service/api/json_v2.php/CN_MarketData.getKLineData?symbol=600050"
      },
      {
        "stock_code": "600050",
        "trade_date": "2026-02-12",
        "open_price": 4.87,
        "close_price": 4.84,
        "high_price": 4.88,
        "low_price": 4.83,
        "volume": 140224151,
        "turnover": 0.0,
        "adj_type": "none",
        "source_type": "sina_history_kline",
        "source_url": "https://money.finance.sina.com.cn/quotes_service/api/json_v2.php/CN_MarketData.getKLineData?symbol=600050"
      },
      {
        "stock_code": "600050",
        "trade_date": "2026-02-13",
        "open_price": 4.84,
        "close_price": 4.8,
        "high_price": 4.86,
        "low_price": 4.8,
        "volume": 156700174,
        "turnover": 0.0,
        "adj_type": "none",
        "source_type": "sina_history_kline",
        "source_url": "https://money.finance.sina.com.cn/quotes_service/api/json_v2.php/CN_MarketData.getKLineData?symbol=600050"
      },
      {
        "stock_code": "600050",
        "trade_date": "2026-02-24",
        "open_price": 4.83,
        "close_price": 4.85,
        "high_price": 4.86,
        "low_price": 4.81,
        "volume": 134095799,
        "turnover": 0.0,
        "adj_type": "none",
        "source_type": "sina_history_kline",
        "source_url": "https://money.finance.sina.com.cn/quotes_service/api/json_v2.php/CN_MarketData.getKLineData?symbol=600050"
      },
      {
        "stock_code": "600050",
        "trade_date": "2026-02-25",
        "open_price": 4.85,
        "close_price": 4.88,
        "high_price": 4.93,
        "low_price": 4.85,
        "volume": 213007849,
        "turnover": 0.0,
        "adj_type": "none",
        "source_type": "sina_history_kline",
        "source_url": "https://money.finance.sina.com.cn/quotes_service/api/json_v2.php/CN_MarketData.getKLineData?symbol=600050"
      },
      {
        "stock_code": "600050",
        "trade_date": "2026-02-26",
        "open_price": 4.89,
        "close_price": 4.88,
        "high_price": 4.91,
        "low_price": 4.85,
        "volume": 156115374,
        "turnover": 0.0,
        "adj_type": "none",
        "source_type": "sina_history_kline",
        "source_url": "https://money.finance.sina.com.cn/quotes_service/api/json_v2.php/CN_MarketData.getKLineData?symbol=600050"
      },
      {
        "stock_code": "600050",
        "trade_date": "2026-02-27",
        "open_price": 4.87,
        "close_price": 4.92,
        "high_price": 4.92,
        "low_price": 4.86,
        "volume": 161645276,
        "turnover": 0.0,
        "adj_type": "none",
        "source_type": "sina_history_kline",
        "source_url": "https://money.finance.sina.com.cn/quotes_service/api/json_v2.php/CN_MarketData.getKLineData?symbol=600050"
      },
      {
        "stock_code": "600050",
        "trade_date": "2026-03-02",
        "open_price": 4.88,
        "close_price": 4.93,
        "high_price": 4.95,
        "low_price": 4.86,
        "volume": 230097379,
        "turnover": 0.0,
        "adj_type": "none",
        "source_type": "sina_history_kline",
        "source_url": "https://money.finance.sina.com.cn/quotes_service/api/json_v2.php/CN_MarketData.getKLineData?symbol=600050"
      },
      {
        "stock_code": "600050",
        "trade_date": "2026-03-03",
        "open_price": 4.92,
        "close_price": 4.89,
        "high_price": 4.97,
        "low_price": 4.88,
        "volume": 295678881,
        "turnover": 0.0,
        "adj_type": "none",
        "source_type": "sina_history_kline",
        "source_url": "https://money.finance.sina.com.cn/quotes_service/api/json_v2.php/CN_MarketData.getKLineData?symbol=600050"
      },
      {
        "stock_code": "600050",
        "trade_date": "2026-03-04",
        "open_price": 4.86,
        "close_price": 4.85,
        "high_price": 4.88,
        "low_price": 4.8,
        "volume": 263651267,
        "turnover": 0.0,
        "adj_type": "none",
        "source_type": "sina_history_kline",
        "source_url": "https://money.finance.sina.com.cn/quotes_service/api/json_v2.php/CN_MarketData.getKLineData?symbol=600050"
      },
      {
        "stock_code": "600050",
        "trade_date": "2026-03-05",
        "open_price": 4.86,
        "close_price": 4.95,
        "high_price": 4.98,
        "low_price": 4.85,
        "volume": 288743327,
        "turnover": 0.0,
        "adj_type": "none",
        "source_type": "sina_history_kline",
        "source_url": "https://money.finance.sina.com.cn/quotes_service/api/json_v2.php/CN_MarketData.getKLineData?symbol=600050"
      },
      {
        "stock_code": "600050",
        "trade_date": "2026-03-06",
        "open_price": 4.94,
        "close_price": 4.97,
        "high_price": 4.97,
        "low_price": 4.91,
        "volume": 153695723,
        "turnover": 0.0,
        "adj_type": "none",
        "source_type": "sina_history_kline",
        "source_url": "https://money.finance.sina.com.cn/quotes_service/api/json_v2.php/CN_MarketData.getKLineData?symbol=600050"
      },
      {
        "stock_code": "600050",
        "trade_date": "2026-03-09",
        "open_price": 4.92,
        "close_price": 4.97,
        "high_price": 4.99,
        "low_price": 4.89,
        "volume": 217584581,
        "turnover": 0.0,
        "adj_type": "none",
        "source_type": "sina_history_kline",
        "source_url": "https://money.finance.sina.com.cn/quotes_service/api/json_v2.php/CN_MarketData.getKLineData?symbol=600050"
      },
      {
        "stock_code": "600050",
        "trade_date": "2026-03-10",
        "open_price": 4.99,
        "close_price": 4.96,
        "high_price": 4.99,
        "low_price": 4.93,
        "volume": 158516598,
        "turnover": 0.0,
        "adj_type": "none",
        "source_type": "sina_history_kline",
        "source_url": "https://money.finance.sina.com.cn/quotes_service/api/json_v2.php/CN_MarketData.getKLineData?symbol=600050"
      },
      {
        "stock_code": "600050",
        "trade_date": "2026-03-11",
        "open_price": 4.96,
        "close_price": 5.04,
        "high_price": 5.05,
        "low_price": 4.95,
        "volume": 238923257,
        "turnover": 0.0,
        "adj_type": "none",
        "source_type": "sina_history_kline",
        "source_url": "https://money.finance.sina.com.cn/quotes_service/api/json_v2.php/CN_MarketData.getKLineData?symbol=600050"
      },
      {
        "stock_code": "600050",
        "trade_date": "2026-03-12",
        "open_price": 5.03,
        "close_price": 5.03,
        "high_price": 5.04,
        "low_price": 4.99,
        "volume": 152199928,
        "turnover": 0.0,
        "adj_type": "none",
        "source_type": "sina_history_kline",
        "source_url": "https://money.finance.sina.com.cn/quotes_service/api/json_v2.php/CN_MarketData.getKLineData?symbol=600050"
      },
      {
        "stock_code": "600050",
        "trade_date": "2026-03-13",
        "open_price": 5.01,
        "close_price": 5.07,
        "high_price": 5.12,
        "low_price": 5.0,
        "volume": 316728173,
        "turnover": 0.0,
        "adj_type": "none",
        "source_type": "sina_history_kline",
        "source_url": "https://money.finance.sina.com.cn/quotes_service/api/json_v2.php/CN_MarketData.getKLineData?symbol=600050"
      },
      {
        "stock_code": "600050",
        "trade_date": "2026-03-16",
        "open_price": 5.09,
        "close_price": 5.03,
        "high_price": 5.09,
        "low_price": 5.02,
        "volume": 187990324,
        "turnover": 0.0,
        "adj_type": "none",
        "source_type": "sina_history_kline",
        "source_url": "https://money.finance.sina.com.cn/quotes_service/api/json_v2.php/CN_MarketData.getKLineData?symbol=600050"
      },
      {
        "stock_code": "600050",
        "trade_date": "2026-03-17",
        "open_price": 5.04,
        "close_price": 4.98,
        "high_price": 5.06,
        "low_price": 4.97,
        "volume": 195932207,
        "turnover": 0.0,
        "adj_type": "none",
        "source_type": "sina_history_kline",
        "source_url": "https://money.finance.sina.com.cn/quotes_service/api/json_v2.php/CN_MarketData.getKLineData?symbol=600050"
      },
      {
        "stock_code": "600050",
        "trade_date": "2026-03-18",
        "open_price": 4.99,
        "close_price": 4.98,
        "high_price": 5.0,
        "low_price": 4.93,
        "volume": 169639264,
        "turnover": 0.0,
        "adj_type": "none",
        "source_type": "sina_history_kline",
        "source_url": "https://money.finance.sina.com.cn/quotes_service/api/json_v2.php/CN_MarketData.getKLineData?symbol=600050"
      },
      {
        "stock_code": "600050",
        "trade_date": "2026-03-19",
        "open_price": 4.95,
        "close_price": 4.96,
        "high_price": 5.0,
        "low_price": 4.94,
        "volume": 181256395,
        "turnover": 0.0,
        "adj_type": "none",
        "source_type": "sina_history_kline",
        "source_url": "https://money.finance.sina.com.cn/quotes_service/api/json_v2.php/CN_MarketData.getKLineData?symbol=600050"
      },
      {
        "stock_code": "600050",
        "trade_date": "2026-03-20",
        "open_price": 4.92,
        "close_price": 4.69,
        "high_price": 4.92,
        "low_price": 4.68,
        "volume": 557236648,
        "turnover": 0.0,
        "adj_type": "none",
        "source_type": "sina_history_kline",
        "source_url": "https://money.finance.sina.com.cn/quotes_service/api/json_v2.php/CN_MarketData.getKLineData?symbol=600050"
      },
      {
        "stock_code": "600050",
        "trade_date": "2026-03-23",
        "open_price": 4.64,
        "close_price": 4.47,
        "high_price": 4.64,
        "low_price": 4.44,
        "volume": 337792636,
        "turnover": 0.0,
        "adj_type": "none",
        "source_type": "sina_history_kline",
        "source_url": "https://money.finance.sina.com.cn/quotes_service/api/json_v2.php/CN_MarketData.getKLineData?symbol=600050"
      },
      {
        "stock_code": "600050",
        "trade_date": "2026-03-24",
        "open_price": 4.49,
        "close_price": 4.54,
        "high_price": 4.55,
        "low_price": 4.45,
        "volume": 178549694,
        "turnover": 0.0,
        "adj_type": "none",
        "source_type": "sina_history_kline",
        "source_url": "https://money.finance.sina.com.cn/quotes_service/api/json_v2.php/CN_MarketData.getKLineData?symbol=600050"
      },
      {
        "stock_code": "600050",
        "trade_date": "2026-03-25",
        "open_price": 4.53,
        "close_price": 4.55,
        "high_price": 4.57,
        "low_price": 4.52,
        "volume": 156930742,
        "turnover": 0.0,
        "adj_type": "none",
        "source_type": "sina_history_kline",
        "source_url": "https://money.finance.sina.com.cn/quotes_service/api/json_v2.php/CN_MarketData.getKLineData?symbol=600050"
      },
      {
        "stock_code": "600050",
        "trade_date": "2026-03-26",
        "open_price": 4.54,
        "close_price": 4.49,
        "high_price": 4.56,
        "low_price": 4.48,
        "volume": 131360015,
        "turnover": 0.0,
        "adj_type": "none",
        "source_type": "sina_history_kline",
        "source_url": "https://money.finance.sina.com.cn/quotes_service/api/json_v2.php/CN_MarketData.getKLineData?symbol=600050"
      },
      {
        "stock_code": "600050",
        "trade_date": "2026-03-27",
        "open_price": 4.46,
        "close_price": 4.49,
        "high_price": 4.5,
        "low_price": 4.44,
        "volume": 111324874,
        "turnover": 0.0,
        "adj_type": "none",
        "source_type": "sina_history_kline",
        "source_url": "https://money.finance.sina.com.cn/quotes_service/api/json_v2.php/CN_MarketData.getKLineData?symbol=600050"
      },
      {
        "stock_code": "600050",
        "trade_date": "2026-03-30",
        "open_price": 4.45,
        "close_price": 4.46,
        "high_price": 4.47,
        "low_price": 4.38,
        "volume": 166228001,
        "turnover": 0.0,
        "adj_type": "none",
        "source_type": "sina_history_kline",
        "source_url": "https://money.finance.sina.com.cn/quotes_service/api/json_v2.php/CN_MarketData.getKLineData?symbol=600050"
      },
      {
        "stock_code": "600050",
        "trade_date": "2026-03-31",
        "open_price": 4.45,
        "close_price": 4.45,
        "high_price": 4.53,
        "low_price": 4.44,
        "volume": 146713670,
        "turnover": 0.0,
        "adj_type": "none",
        "source_type": "sina_history_kline",
        "source_url": "https://money.finance.sina.com.cn/quotes_service/api/json_v2.php/CN_MarketData.getKLineData?symbol=600050"
      },
      {
        "stock_code": "600050",
        "trade_date": "2026-04-01",
        "open_price": 4.5,
        "close_price": 4.48,
        "high_price": 4.51,
        "low_price": 4.47,
        "volume": 113110847,
        "turnover": 0.0,
        "adj_type": "none",
        "source_type": "sina_history_kline",
        "source_url": "https://money.finance.sina.com.cn/quotes_service/api/json_v2.php/CN_MarketData.getKLineData?symbol=600050"
      },
      {
        "stock_code": "600050",
        "trade_date": "2026-04-02",
        "open_price": 4.47,
        "close_price": 4.43,
        "high_price": 4.48,
        "low_price": 4.41,
        "volume": 121358547,
        "turnover": 0.0,
        "adj_type": "none",
        "source_type": "sina_history_kline",
        "source_url": "https://money.finance.sina.com.cn/quotes_service/api/json_v2.php/CN_MarketData.getKLineData?symbol=600050"
      },
      {
        "stock_code": "600050",
        "trade_date": "2026-04-03",
        "open_price": 4.43,
        "close_price": 4.46,
        "high_price": 4.48,
        "low_price": 4.43,
        "volume": 142470095,
        "turnover": 0.0,
        "adj_type": "none",
        "source_type": "sina_history_kline",
        "source_url": "https://money.finance.sina.com.cn/quotes_service/api/json_v2.php/CN_MarketData.getKLineData?symbol=600050"
      },
      {
        "stock_code": "600050",
        "trade_date": "2026-04-07",
        "open_price": 4.47,
        "close_price": 4.47,
        "high_price": 4.49,
        "low_price": 4.46,
        "volume": 84765675,
        "turnover": 0.0,
        "adj_type": "none",
        "source_type": "sina_history_kline",
        "source_url": "https://money.finance.sina.com.cn/quotes_service/api/json_v2.php/CN_MarketData.getKLineData?symbol=600050"
      },
      {
        "stock_code": "600050",
        "trade_date": "2026-04-08",
        "open_price": 4.5,
        "close_price": 4.57,
        "high_price": 4.57,
        "low_price": 4.5,
        "volume": 189336780,
        "turnover": 0.0,
        "adj_type": "none",
        "source_type": "sina_history_kline",
        "source_url": "https://money.finance.sina.com.cn/quotes_service/api/json_v2.php/CN_MarketData.getKLineData?symbol=600050"
      },
      {
        "stock_code": "600050",
        "trade_date": "2026-04-09",
        "open_price": 4.55,
        "close_price": 4.52,
        "high_price": 4.55,
        "low_price": 4.5,
        "volume": 108187128,
        "turnover": 0.0,
        "adj_type": "none",
        "source_type": "sina_history_kline",
        "source_url": "https://money.finance.sina.com.cn/quotes_service/api/json_v2.php/CN_MarketData.getKLineData?symbol=600050"
      },
      {
        "stock_code": "600050",
        "trade_date": "2026-04-10",
        "open_price": 4.53,
        "close_price": 4.56,
        "high_price": 4.59,
        "low_price": 4.52,
        "volume": 131507889,
        "turnover": 0.0,
        "adj_type": "none",
        "source_type": "sina_history_kline",
        "source_url": "https://money.finance.sina.com.cn/quotes_service/api/json_v2.php/CN_MarketData.getKLineData?symbol=600050"
      },
      {
        "stock_code": "600050",
        "trade_date": "2026-04-13",
        "open_price": 4.55,
        "close_price": 4.56,
        "high_price": 4.57,
        "low_price": 4.53,
        "volume": 86278614,
        "turnover": 0.0,
        "adj_type": "none",
        "source_type": "sina_history_kline",
        "source_url": "https://money.finance.sina.com.cn/quotes_service/api/json_v2.php/CN_MarketData.getKLineData?symbol=600050"
      },
      {
        "stock_code": "600050",
        "trade_date": "2026-04-14",
        "open_price": 4.56,
        "close_price": 4.58,
        "high_price": 4.58,
        "low_price": 4.55,
        "volume": 92171092,
        "turnover": 0.0,
        "adj_type": "none",
        "source_type": "sina_history_kline",
        "source_url": "https://money.finance.sina.com.cn/quotes_service/api/json_v2.php/CN_MarketData.getKLineData?symbol=600050"
      },
      {
        "stock_code": "600050",
        "trade_date": "2026-04-15",
        "open_price": 4.58,
        "close_price": 4.57,
        "high_price": 4.6,
        "low_price": 4.57,
        "volume": 119352237,
        "turnover": 0.0,
        "adj_type": "none",
        "source_type": "sina_history_kline",
        "source_url": "https://money.finance.sina.com.cn/quotes_service/api/json_v2.php/CN_MarketData.getKLineData?symbol=600050"
      },
      {
        "stock_code": "600050",
        "trade_date": "2026-04-16",
        "open_price": 4.58,
        "close_price": 4.6,
        "high_price": 4.6,
        "low_price": 4.55,
        "volume": 139907471,
        "turnover": 0.0,
        "adj_type": "none",
        "source_type": "sina_history_kline",
        "source_url": "https://money.finance.sina.com.cn/quotes_service/api/json_v2.php/CN_MarketData.getKLineData?symbol=600050"
      },
      {
        "stock_code": "600050",
        "trade_date": "2026-04-17",
        "open_price": 4.6,
        "close_price": 4.64,
        "high_price": 4.7,
        "low_price": 4.59,
        "volume": 232597084,
        "turnover": 0.0,
        "adj_type": "none",
        "source_type": "sina_history_kline",
        "source_url": "https://money.finance.sina.com.cn/quotes_service/api/json_v2.php/CN_MarketData.getKLineData?symbol=600050"
      },
      {
        "stock_code": "600050",
        "trade_date": "2026-04-20",
        "open_price": 4.63,
        "close_price": 4.59,
        "high_price": 4.64,
        "low_price": 4.59,
        "volume": 148318438,
        "turnover": 0.0,
        "adj_type": "none",
        "source_type": "sina_history_kline",
        "source_url": "https://money.finance.sina.com.cn/quotes_service/api/json_v2.php/CN_MarketData.getKLineData?symbol=600050"
      },
      {
        "stock_code": "600050",
        "trade_date": "2026-04-21",
        "open_price": 4.58,
        "close_price": 4.66,
        "high_price": 4.66,
        "low_price": 4.57,
        "volume": 150642611,
        "turnover": 0.0,
        "adj_type": "none",
        "source_type": "sina_history_kline",
        "source_url": "https://money.finance.sina.com.cn/quotes_service/api/json_v2.php/CN_MarketData.getKLineData?symbol=600050"
      },
      {
        "stock_code": "600050",
        "trade_date": "2026-04-22",
        "open_price": 4.59,
        "close_price": 4.5,
        "high_price": 4.6,
        "low_price": 4.49,
        "volume": 343073638,
        "turnover": 0.0,
        "adj_type": "none",
        "source_type": "sina_history_kline",
        "source_url": "https://money.finance.sina.com.cn/quotes_service/api/json_v2.php/CN_MarketData.getKLineData?symbol=600050"
      },
      {
        "stock_code": "600050",
        "trade_date": "2026-04-23",
        "open_price": 4.5,
        "close_price": 4.5,
        "high_price": 4.51,
        "low_price": 4.47,
        "volume": 167789336,
        "turnover": 0.0,
        "adj_type": "none",
        "source_type": "sina_history_kline",
        "source_url": "https://money.finance.sina.com.cn/quotes_service/api/json_v2.php/CN_MarketData.getKLineData?symbol=600050"
      }
    ]
  }
}