{
  "generated_at": "2026-04-23T17:11:29.542353+00:00",
  "payload": {
    "income_statements": [],
    "balance_sheets": [],
    "cashflow_statements": [],
    "financial_metrics": [],
    "financial_notes": [],
    "business_segments": [],
    "stock_daily": [
      {
        "stock_code": "600154",
        "trade_date": "2026-01-01",
        "open_price": 92.8,
        "close_price": 84.6,
        "high_price": 93.62,
        "low_price": 82.36,
        "volume": 44920207,
        "turnover": 3800249512.2,
        "source_type": "stress_mock"
      },
      {
        "stock_code": "600154",
        "trade_date": "2026-01-02",
        "open_price": 91.81,
        "close_price": 84.92,
        "high_price": 95.41,
        "low_price": 81.35,
        "volume": 5240486,
        "turnover": 445022071.12,
        "source_type": "stress_mock"
      },
      {
        "stock_code": "600154",
        "trade_date": "2026-01-03",
        "open_price": 120.03,
        "close_price": 115.74,
        "high_price": 123.32,
        "low_price": 112.31,
        "volume": 4634776,
        "turnover": 536428974.24,
        "source_type": "stress_mock"
      },
      {
        "stock_code": "600154",
        "trade_date": "2026-01-04",
        "open_price": 122.14,
        "close_price": 111.39,
        "high_price": 122.95,
        "low_price": 106.21,
        "volume": 6579982,
        "turnover": 732944194.98,
        "source_type": "stress_mock"
      },
      {
        "stock_code": "600154",
        "trade_date": "2026-01-05",
        "open_price": 97.85,
        "close_price": 98.77,
        "high_price": 103.35,
        "low_price": 93.08,
        "volume": 31830776,
        "turnover": 3143925745.52,
        "source_type": "stress_mock"
      },
      {
        "stock_code": "600154",
        "trade_date": "2026-01-06",
        "open_price": 97.78,
        "close_price": 96.36,
        "high_price": 99.42,
        "low_price": 92.19,
        "volume": 10722702,
        "turnover": 1033239564.72,
        "source_type": "stress_mock"
      },
      {
        "stock_code": "600154",
        "trade_date": "2026-01-07",
        "open_price": 98.63,
        "close_price": 99.4,
        "high_price": 102.31,
        "low_price": 94.05,
        "volume": 7764915,
        "turnover": 771832551.0,
        "source_type": "stress_mock"
      },
      {
        "stock_code": "600154",
        "trade_date": "2026-01-08",
        "open_price": 131.87,
        "close_price": 132.31,
        "high_price": 134.19,
        "low_price": 128.66,
        "volume": 21290168,
        "turnover": 2816902128.08,
        "source_type": "stress_mock"
      },
      {
        "stock_code": "600154",
        "trade_date": "2026-01-09",
        "open_price": 141.16,
        "close_price": 129.41,
        "high_price": 143.18,
        "low_price": 123.92,
        "volume": 16266883,
        "turnover": 2105097329.03,
        "source_type": "stress_mock"
      },
      {
        "stock_code": "600154",
        "trade_date": "2026-01-10",
        "open_price": 52.16,
        "close_price": 47.25,
        "high_price": 54.11,
        "low_price": 45.96,
        "volume": 17495950,
        "turnover": 826683637.5,
        "source_type": "stress_mock"
      },
      {
        "stock_code": "600154",
        "trade_date": "2026-01-11",
        "open_price": 140.83,
        "close_price": 142.8,
        "high_price": 146.64,
        "low_price": 140.18,
        "volume": 8276630,
        "turnover": 1181902764.0,
        "source_type": "stress_mock"
      },
      {
        "stock_code": "600154",
        "trade_date": "2026-01-12",
        "open_price": 74.33,
        "close_price": 77.26,
        "high_price": 78.06,
        "low_price": 71.58,
        "volume": 17884400,
        "turnover": 1381748744.0,
        "source_type": "stress_mock"
      },
      {
        "stock_code": "600154",
        "trade_date": "2026-01-13",
        "open_price": 115.87,
        "close_price": 115.92,
        "high_price": 118.12,
        "low_price": 113.63,
        "volume": 7213687,
        "turnover": 836210597.04,
        "source_type": "stress_mock"
      },
      {
        "stock_code": "600154",
        "trade_date": "2026-01-14",
        "open_price": 97.87,
        "close_price": 106.96,
        "high_price": 110.78,
        "low_price": 93.48,
        "volume": 33296434,
        "turnover": 3561386580.64,
        "source_type": "stress_mock"
      },
      {
        "stock_code": "600154",
        "trade_date": "2026-01-15",
        "open_price": 70.17,
        "close_price": 72.74,
        "high_price": 74.24,
        "low_price": 68.66,
        "volume": 44236847,
        "turnover": 3217788250.78,
        "source_type": "stress_mock"
      },
      {
        "stock_code": "600154",
        "trade_date": "2026-01-16",
        "open_price": 84.08,
        "close_price": 79.21,
        "high_price": 86.28,
        "low_price": 75.41,
        "volume": 5819730,
        "turnover": 460980813.3,
        "source_type": "stress_mock"
      },
      {
        "stock_code": "600154",
        "trade_date": "2026-01-17",
        "open_price": 77.48,
        "close_price": 83.23,
        "high_price": 86.62,
        "low_price": 76.72,
        "volume": 9019705,
        "turnover": 750710047.15,
        "source_type": "stress_mock"
      },
      {
        "stock_code": "600154",
        "trade_date": "2026-01-18",
        "open_price": 92.8,
        "close_price": 88.96,
        "high_price": 94.8,
        "low_price": 88.36,
        "volume": 43964393,
        "turnover": 3911072401.28,
        "source_type": "stress_mock"
      },
      {
        "stock_code": "600154",
        "trade_date": "2026-01-19",
        "open_price": 137.15,
        "close_price": 133.55,
        "high_price": 142.67,
        "low_price": 130.13,
        "volume": 49677736,
        "turnover": 6634461642.8,
        "source_type": "stress_mock"
      },
      {
        "stock_code": "600154",
        "trade_date": "2026-01-20",
        "open_price": 81.59,
        "close_price": 79.07,
        "high_price": 85.52,
        "low_price": 78.71,
        "volume": 24961438,
        "turnover": 1973700902.66,
        "source_type": "stress_mock"
      },
      {
        "stock_code": "600154",
        "trade_date": "2026-01-21",
        "open_price": 133.44,
        "close_price": 138.05,
        "high_price": 140.22,
        "low_price": 131.78,
        "volume": 31066157,
        "turnover": 4288682973.85,
        "source_type": "stress_mock"
      },
      {
        "stock_code": "600154",
        "trade_date": "2026-01-22",
        "open_price": 147.74,
        "close_price": 140.65,
        "high_price": 151.0,
        "low_price": 135.68,
        "volume": 21867163,
        "turnover": 3075616475.95,
        "source_type": "stress_mock"
      },
      {
        "stock_code": "600154",
        "trade_date": "2026-01-23",
        "open_price": 66.47,
        "close_price": 70.65,
        "high_price": 72.69,
        "low_price": 65.5,
        "volume": 41692587,
        "turnover": 2945581271.55,
        "source_type": "stress_mock"
      },
      {
        "stock_code": "600154",
        "trade_date": "2026-01-24",
        "open_price": 52.17,
        "close_price": 51.2,
        "high_price": 52.53,
        "low_price": 48.65,
        "volume": 21250510,
        "turnover": 1088026112.0,
        "source_type": "stress_mock"
      },
      {
        "stock_code": "600154",
        "trade_date": "2026-01-25",
        "open_price": 62.96,
        "close_price": 63.81,
        "high_price": 64.85,
        "low_price": 61.49,
        "volume": 17356339,
        "turnover": 1107507991.59,
        "source_type": "stress_mock"
      },
      {
        "stock_code": "600154",
        "trade_date": "2026-01-26",
        "open_price": 60.99,
        "close_price": 64.87,
        "high_price": 65.05,
        "low_price": 59.23,
        "volume": 7192293,
        "turnover": 466564046.91,
        "source_type": "stress_mock"
      },
      {
        "stock_code": "600154",
        "trade_date": "2026-01-27",
        "open_price": 94.73,
        "close_price": 93.17,
        "high_price": 97.06,
        "low_price": 91.29,
        "volume": 12339337,
        "turnover": 1149656028.29,
        "source_type": "stress_mock"
      },
      {
        "stock_code": "600154",
        "trade_date": "2026-01-28",
        "open_price": 81.96,
        "close_price": 74.12,
        "high_price": 83.77,
        "low_price": 73.3,
        "volume": 13612630,
        "turnover": 1008968135.6,
        "source_type": "stress_mock"
      },
      {
        "stock_code": "600154",
        "trade_date": "2026-01-29",
        "open_price": 137.73,
        "close_price": 147.82,
        "high_price": 148.36,
        "low_price": 134.81,
        "volume": 15756927,
        "turnover": 2329188949.14,
        "source_type": "stress_mock"
      },
      {
        "stock_code": "600154",
        "trade_date": "2026-01-30",
        "open_price": 136.87,
        "close_price": 141.16,
        "high_price": 147.52,
        "low_price": 131.3,
        "volume": 39583682,
        "turnover": 5587632551.12,
        "source_type": "stress_mock"
      }
    ],
    "sync_vector_index": false
  }
}
