{
  "generated_at": "2026-04-23T10:14:48.839680+00:00",
  "payload": {
    "company_master": {
      "stock_code": "990479",
      "stock_name": "航能源79股份有限公司",
      "full_name": "银机械79股份有限公司",
      "exchange": "SSE",
      "industry_level1": "非银金融",
      "industry_level2": "化学制品",
      "listing_date": "2014-02-06",
      "status": "active",
      "source_type": "mock_stress_test"
    },
    "company_profile": {
      "stock_code": "990479",
      "business_summary": "这是海集团公司的业务简介，用于压测数据。",
      "core_products_json": [
        "产品A479",
        "产品B479"
      ],
      "main_segments_json": [
        {
          "name": "业务板块479A",
          "ratio": 0.6
        },
        {
          "name": "业务板块479B",
          "ratio": 0.4
        }
      ],
      "market_position": "压测用模拟数据"
    },
    "industries": [],
    "company_industries": []
  }
}