{
  "generated_at": "2026-04-23T10:14:48.839680+00:00",
  "payload": {
    "company_master": {
      "stock_code": "990300",
      "stock_name": "华材料0股份有限公司",
      "full_name": "西金融0股份有限公司",
      "exchange": "SZSE",
      "industry_level1": "房地产",
      "industry_level2": "证券",
      "listing_date": "2016-08-12",
      "status": "active",
      "source_type": "mock_stress_test"
    },
    "company_profile": {
      "stock_code": "990300",
      "business_summary": "这是金医药公司的业务简介，用于压测数据。",
      "core_products_json": [
        "产品A300",
        "产品B300"
      ],
      "main_segments_json": [
        {
          "name": "业务板块300A",
          "ratio": 0.6
        },
        {
          "name": "业务板块300B",
          "ratio": 0.4
        }
      ],
      "market_position": "压测用模拟数据"
    },
    "industries": [],
    "company_industries": []
  }
}